resampler/__init__.py
resampler/__init__.pyi
resampler-1.0.1.dist-info/licenses/LICENSE
resampler-1.0.1.dist-info/WHEEL
resampler-1.0.1.dist-info/METADATA
resampler-1.0.1.dist-info/RECORD
