Metadata-Version: 2.4
Name: resampler
Version: 1.0.1
Summary: Fast differentiable resizing and warping of arbitrary grids
Keywords: 
Author-email: Hugues Hoppe <hhoppe@gmail.com>
Requires-Python: >=3.10
Classifier: Intended Audience :: Developers
Classifier: Intended Audience :: Education
Classifier: Intended Audience :: Science/Research
Classifier: License :: OSI Approved :: MIT License
Classifier: Operating System :: OS Independent
Classifier: Programming Language :: Python :: 3
Classifier: Topic :: Scientific/Engineering :: Image Processing
Classifier: Topic :: Software Development :: Libraries :: Python Modules
License-File: LICENSE
Requires-Dist: numpy
Requires-Dist: scipy
Project-URL: documentation, https://hhoppe.github.io/resampler/resampler.html
Project-URL: homepage, https://colab.research.google.com/github/hhoppe/resampler/blob/main/resampler_notebook.ipynb
Project-URL: repository, https://github.com/hhoppe/resampler
Provides-Extra: dev
